yt_concate_py/__init__.py
yt_concate_py/logger.py
yt_concate_py/main.py
yt_concate_py/settings.py
yt_concate_py/utils.py
yt_concate_py/model/__init__.py
yt_concate_py/model/found.py
yt_concate_py/model/yt.py
yt_concate_py/pipeline/__init__.py
yt_concate_py/pipeline/pipeline.py
yt_concate_py/pipeline/steps/__init__.py
yt_concate_py/pipeline/steps/download_captions.py
yt_concate_py/pipeline/steps/download_videos.py
yt_concate_py/pipeline/steps/edit_video.py
yt_concate_py/pipeline/steps/get_video_list.py
yt_concate_py/pipeline/steps/initialize_yt.py
yt_concate_py/pipeline/steps/postflight.py
yt_concate_py/pipeline/steps/prefligt.py
yt_concate_py/pipeline/steps/read_captions.py
yt_concate_py/pipeline/steps/search.py
yt_concate_py/pipeline/steps/step.py
yt_concate_py-0.1.6.dist-info/LICENSE
yt_concate_py-0.1.6.dist-info/METADATA
yt_concate_py-0.1.6.dist-info/WHEEL
yt_concate_py-0.1.6.dist-info/top_level.txt
yt_concate_py-0.1.6.dist-info/RECORD
