Metadata-Version: 2.1
Name: yt-concate-py
Version: 0.1.6
Summary: Produce a consolidated video by concatenating YouTube video clips that mention a specific word.
Home-page: https://github.com/whygreedy/yt-concate-py
Author: Cindy Yeh
Author-email: cindyyeah9@gmail.com
License: MIT
Classifier: License :: OSI Approved :: MIT License
Classifier: Programming Language :: Python
Classifier: Programming Language :: Python :: 3
Classifier: Programming Language :: Python :: 3.6
Classifier: Programming Language :: Python :: Implementation :: CPython
Classifier: Programming Language :: Python :: Implementation :: PyPy
Requires-Python: >=3.9.0
License-File: LICENSE
Requires-Dist: moviepy
Requires-Dist: pytubefix
Requires-Dist: requests
Requires-Dist: urllib3
Requires-Dist: python-dotenv
